Metadata-Version: 2.1
Name: updoon
Version: 0.5.0
Summary: classes and functions to download or scrape data
Home-page: http://github.com/waalfisk/updoon
Author: Ulf Hamster
Author-email: 554c46@gmail.com
License: MIT
Platform: UNKNOWN
Requires-Python: >=3
